multi_stat_analysis/CanvasPanel.py
multi_stat_analysis/CurveFit.py
multi_stat_analysis/Dialogs.py
multi_stat_analysis/GraphDialogs.py
multi_stat_analysis/MultiscaleData.py
multi_stat_analysis/MultiscaleImporter.py
multi_stat_analysis/StatsTestsUI.py
multi_stat_analysis/Workbook.py
multi_stat_analysis/__init__.py
multi_stat_analysis/__main__.py
multi_stat_analysis/MountainsImporter/ImportUtils.py
multi_stat_analysis/MountainsImporter/Importer.py
multi_stat_analysis/MountainsImporter/__init__.py
multi_stat_analysis/MountainsImporter/__pycache__/ImportUtils.cpython-38.opt-1.pyc
multi_stat_analysis/MountainsImporter/__pycache__/ImportUtils.cpython-38.pyc
multi_stat_analysis/MountainsImporter/__pycache__/Importer.cpython-38.opt-1.pyc
multi_stat_analysis/MountainsImporter/__pycache__/Importer.cpython-38.pyc
multi_stat_analysis/MountainsImporter/__pycache__/__init__.cpython-38.opt-1.pyc
multi_stat_analysis/MountainsImporter/__pycache__/__init__.cpython-38.pyc
multi_stat_analysis/__pycache__/CanvasPanel.cpython-38.opt-1.pyc
multi_stat_analysis/__pycache__/CanvasPanel.cpython-38.pyc
multi_stat_analysis/__pycache__/CurveFit.cpython-38.opt-1.pyc
multi_stat_analysis/__pycache__/CurveFit.cpython-38.pyc
multi_stat_analysis/__pycache__/Dialogs.cpython-38.opt-1.pyc
multi_stat_analysis/__pycache__/Dialogs.cpython-38.pyc
multi_stat_analysis/__pycache__/GraphDialogs.cpython-38.opt-1.pyc
multi_stat_analysis/__pycache__/GraphDialogs.cpython-38.pyc
multi_stat_analysis/__pycache__/MultiscaleData.cpython-38.pyc
multi_stat_analysis/__pycache__/MultiscaleImporter.cpython-38.pyc
multi_stat_analysis/__pycache__/PlotData.cpython-38.opt-1.pyc
multi_stat_analysis/__pycache__/PlotData.cpython-38.pyc
multi_stat_analysis/__pycache__/StatsTestsUI.cpython-38.opt-1.pyc
multi_stat_analysis/__pycache__/StatsTestsUI.cpython-38.pyc
multi_stat_analysis/__pycache__/SurfaceImporter.cpython-38.pyc
multi_stat_analysis/__pycache__/Workbook.cpython-38.opt-1.pyc
multiscale_statistical_analysis-0.5.0.dist-info/LICENSE
multiscale_statistical_analysis-0.5.0.dist-info/METADATA
multiscale_statistical_analysis-0.5.0.dist-info/WHEEL
multiscale_statistical_analysis-0.5.0.dist-info/top_level.txt
multiscale_statistical_analysis-0.5.0.dist-info/RECORD
