Metadata-Version: 2.1
Name: multiscale-statistical-analysis
Version: 0.5.0
Summary: Multiscale regression analysis software, which uses multiscale area data exported from MountainsMap®.
Home-page: UNKNOWN
Author: Matthew Spofford, Nathaniel Rutkowski
Author-email: mespofford@wpi.edu
License: MIT
Platform: UNKNOWN
Classifier: Development Status :: 4 - Beta
Classifier: Programming Language :: Python :: 3 :: Only
Classifier: Framework :: Setuptools Plugin
Classifier: Framework :: Matplotlib
Classifier: Environment :: Win32 (MS Windows)
Classifier: License :: OSI Approved :: MIT License
Classifier: Topic :: Scientific/Engineering
Classifier: Natural Language :: English
Requires-Dist: numpy (==1.18.5)
Requires-Dist: wxPython (==4.1.0)
Requires-Dist: scipy (==1.5.0)
Requires-Dist: matplotlib (==3.2.2)
Requires-Dist: openpyxl (==3.0.3)
Requires-Dist: aenum (==2.2.3)
